{
 "cells": [
  {
   "cell_type": "code",
   "execution_count": 48,
   "metadata": {},
   "outputs": [
    {
     "name": "stdout",
     "output_type": "stream",
     "text": [
      "new y cap values : [0.8, 1.6, 2.4000000000000004, 3.2]\n",
      "10.799999999999999\n",
      "1.88\n",
      "new y cap values : [1.88, 3.76, 5.64, 7.52]\n",
      "0.10800000000000021\n",
      "1.8907999999999998\n",
      "new y cap values : [1.8907999999999998, 3.7815999999999996, 5.6724, 7.563199999999999]\n",
      "0.08943480000000026\n",
      "1.89974348\n",
      "new y cap values : [1.89974348, 3.79948696, 5.69923044, 7.59897392]\n",
      "0.07538527351882807\n",
      "1.9072820073518828\n",
      "new y cap values : [1.9072820073518828, 3.8145640147037656, 5.721846022055648, 7.629128029407531]\n",
      "0.06447469620522239\n",
      "1.9137294769724051\n",
      "new y cap values : [1.9137294769724051, 3.8274589539448103, 5.741188430917216, 7.654917907889621]\n",
      "0.05581952357591075\n",
      "1.9193114293299962\n",
      "new y cap values : [1.9193114293299962, 3.8386228586599924, 5.757934287989989, 7.677245717319985]\n",
      "0.04882984077576144\n",
      "1.9241944134075724\n",
      "new y cap values : [1.9241944134075724, 3.8483888268151447, 5.772583240222717, 7.696777653630289]\n",
      "0.04309865218966531\n",
      "1.928504278626539\n",
      "new y cap values : [1.928504278626539, 3.857008557253078, 5.785512835879617, 7.714017114506156]\n",
      "0.038337286310336824\n",
      "1.9323380072575727\n",
      "new y cap values : [1.9323380072575727, 3.8646760145151453, 5.797014021772718, 7.729352029030291]\n",
      "0.034336089464072204\n",
      "1.93577161620398\n",
      "{10.799999999999999: 1.88, 0.10800000000000021: 1.8907999999999998, 0.08943480000000026: 1.89974348, 0.07538527351882807: 1.9072820073518828, 0.06447469620522239: 1.9137294769724051, 0.05581952357591075: 1.9193114293299962, 0.04882984077576144: 1.9241944134075724, 0.04309865218966531: 1.928504278626539, 0.038337286310336824: 1.9323380072575727, 0.034336089464072204: 1.93577161620398}\n",
      "min error---> 0.034336089464072204\n",
      "opt weight----> 1.93577161620398\n"
     ]
    }
   ],
   "source": [
    "\n",
    "import dis\n",
    "\n",
    "def find_ycap(x,w):\n",
    "    y_cap = []\n",
    "    for i in x:\n",
    "        y_cap.append(i*w)\n",
    "    return y_cap\n",
    "\n",
    "def error(y,y_cap,e):\n",
    "    for i in range(len(y)):\n",
    "        e += (y[i] - y_cap[i])**2\n",
    "    #e = [(y[i] - y_cap[i])**2 for i in range(len(y))]\n",
    "    Error = e/len(y) \n",
    "    #Error = [i/len(y) for i in e]\n",
    "    print(Error)    \n",
    "    return Error\n",
    "            \n",
    "def weight(w,Error,lr):\n",
    "    wc = w - (-(Error*lr))  \n",
    "    print(wc)\n",
    "    return wc\n",
    "    \n",
    "def main():\n",
    "    x = [1,2,3,4]\n",
    "    y = [2,4,6,8]\n",
    "    w = 0.8\n",
    "    wc,e,Error = 0,0,0\n",
    "    Error_weight_dict = {}\n",
    "    lr =  0.1\n",
    "    for i in range(10):\n",
    "        y_cap = find_ycap(x,w).copy()\n",
    "        print(f\"new y cap values : {y_cap}\")\n",
    "        Error = error(y,y_cap,e)\n",
    "        w = weight(w,Error,lr)\n",
    "        Error_weight_dict[Error] = w\n",
    "    print(Error_weight_dict)\n",
    "    print(\"min error--->\", min(Error_weight_dict))\n",
    "    print(\"opt weight---->\", Error_weight_dict[min(Error_weight_dict)])\n",
    "\n",
    "    \n",
    "if __name__ == \"__main__\":\n",
    "    main()"
   ]
  },
  {
   "cell_type": "code",
   "execution_count": 44,
   "metadata": {},
   "outputs": [
    {
     "name": "stdout",
     "output_type": "stream",
     "text": [
      " 25           0 LOAD_CONST               1 (1)\n",
      "              2 LOAD_CONST               2 (2)\n",
      "              4 LOAD_CONST               3 (3)\n",
      "              6 LOAD_CONST               4 (4)\n",
      "              8 BUILD_LIST               4\n",
      "             10 STORE_FAST               0 (x)\n",
      "\n",
      " 26          12 LOAD_CONST               2 (2)\n",
      "             14 LOAD_CONST               4 (4)\n",
      "             16 LOAD_CONST               5 (6)\n",
      "             18 LOAD_CONST               6 (8)\n",
      "             20 BUILD_LIST               4\n",
      "             22 STORE_FAST               1 (y)\n",
      "\n",
      " 27          24 LOAD_CONST               7 (0.8)\n",
      "             26 STORE_FAST               2 (w)\n",
      "\n",
      " 28          28 LOAD_CONST              14 ((0, 0, 0))\n",
      "             30 UNPACK_SEQUENCE          3\n",
      "             32 STORE_FAST               3 (wc)\n",
      "             34 STORE_FAST               4 (e)\n",
      "             36 STORE_FAST               5 (Error)\n",
      "\n",
      " 29          38 BUILD_MAP                0\n",
      "             40 STORE_FAST               6 (Error_weight_dict)\n",
      "\n",
      " 30          42 LOAD_CONST               9 (0.1)\n",
      "             44 STORE_FAST               7 (lr)\n",
      "\n",
      " 31          46 SETUP_LOOP              76 (to 124)\n",
      "             48 LOAD_GLOBAL              0 (range)\n",
      "             50 LOAD_CONST              10 (10)\n",
      "             52 CALL_FUNCTION            1\n",
      "             54 GET_ITER\n",
      "        >>   56 FOR_ITER                64 (to 122)\n",
      "             58 STORE_FAST               8 (i)\n",
      "\n",
      " 32          60 LOAD_GLOBAL              1 (find_ycap)\n",
      "             62 LOAD_FAST                0 (x)\n",
      "             64 LOAD_FAST                2 (w)\n",
      "             66 CALL_FUNCTION            2\n",
      "             68 LOAD_ATTR                2 (copy)\n",
      "             70 CALL_FUNCTION            0\n",
      "             72 STORE_FAST               9 (y_cap)\n",
      "\n",
      " 33          74 LOAD_GLOBAL              3 (print)\n",
      "             76 LOAD_CONST              11 ('new y cap values : ')\n",
      "             78 LOAD_FAST                9 (y_cap)\n",
      "             80 FORMAT_VALUE             0\n",
      "             82 BUILD_STRING             2\n",
      "             84 CALL_FUNCTION            1\n",
      "             86 POP_TOP\n",
      "\n",
      " 34          88 LOAD_GLOBAL              4 (error)\n",
      "             90 LOAD_FAST                1 (y)\n",
      "             92 LOAD_FAST                9 (y_cap)\n",
      "             94 LOAD_FAST                4 (e)\n",
      "             96 CALL_FUNCTION            3\n",
      "             98 STORE_FAST               5 (Error)\n",
      "\n",
      " 35         100 LOAD_GLOBAL              5 (weight)\n",
      "            102 LOAD_FAST                2 (w)\n",
      "            104 LOAD_FAST                5 (Error)\n",
      "            106 LOAD_FAST                7 (lr)\n",
      "            108 CALL_FUNCTION            3\n",
      "            110 STORE_FAST               2 (w)\n",
      "\n",
      " 36         112 LOAD_FAST                2 (w)\n",
      "            114 LOAD_FAST                6 (Error_weight_dict)\n",
      "            116 LOAD_FAST                5 (Error)\n",
      "            118 STORE_SUBSCR\n",
      "            120 JUMP_ABSOLUTE           56\n",
      "        >>  122 POP_BLOCK\n",
      "\n",
      " 37     >>  124 LOAD_GLOBAL              3 (print)\n",
      "            126 LOAD_FAST                6 (Error_weight_dict)\n",
      "            128 CALL_FUNCTION            1\n",
      "            130 POP_TOP\n",
      "\n",
      " 38         132 LOAD_GLOBAL              3 (print)\n",
      "            134 LOAD_CONST              12 ('min error--->')\n",
      "            136 LOAD_GLOBAL              6 (min)\n",
      "            138 LOAD_FAST                6 (Error_weight_dict)\n",
      "            140 CALL_FUNCTION            1\n",
      "            142 CALL_FUNCTION            2\n",
      "            144 POP_TOP\n",
      "\n",
      " 39         146 LOAD_GLOBAL              3 (print)\n",
      "            148 LOAD_CONST              13 ('opt weight---->')\n",
      "            150 LOAD_FAST                6 (Error_weight_dict)\n",
      "            152 LOAD_GLOBAL              6 (min)\n",
      "            154 LOAD_FAST                6 (Error_weight_dict)\n",
      "            156 CALL_FUNCTION            1\n",
      "            158 BINARY_SUBSCR\n",
      "            160 CALL_FUNCTION            2\n",
      "            162 POP_TOP\n",
      "            164 LOAD_CONST               0 (None)\n",
      "            166 RETURN_VALUE\n"
     ]
    }
   ],
   "source": [
    "dis.dis(main)"
   ]
  },
  {
   "cell_type": "code",
   "execution_count": 30,
   "metadata": {
    "scrolled": true
   },
   "outputs": [
    {
     "name": "stdout",
     "output_type": "stream",
     "text": [
      "1\n",
      "y_hat---> [0.8, 1.6, 2.4000000000000004, 3.2]\n",
      "e---> [1.2, 2.4, 3.5999999999999996, 4.8]\n",
      "sqr_e---> [1.44, 5.76, 12.959999999999997, 23.04]\n",
      "E---> 10.799999999999999\n",
      "w---> 1.88\n",
      "-------------------\n",
      "E_w[E] : 1.88\n",
      "2\n",
      "y_hat---> [1.88, 3.76, 5.64, 7.52]\n",
      "e---> [0.1200000000000001, 0.2400000000000002, 0.3600000000000003, 0.4800000000000004]\n",
      "sqr_e---> [0.014400000000000026, 0.0576000000000001, 0.12960000000000024, 0.2304000000000004]\n",
      "E---> 0.10800000000000021\n",
      "w---> 1.8907999999999998\n",
      "-------------------\n",
      "E_w[E] : 1.8907999999999998\n",
      "3\n",
      "y_hat---> [1.8907999999999998, 3.7815999999999996, 5.6724, 7.563199999999999]\n",
      "e---> [0.10920000000000019, 0.21840000000000037, 0.32760000000000034, 0.43680000000000074]\n",
      "sqr_e---> [0.01192464000000004, 0.04769856000000016, 0.10732176000000022, 0.19079424000000064]\n",
      "E---> 0.08943480000000026\n",
      "w---> 1.89974348\n",
      "-------------------\n",
      "E_w[E] : 1.89974348\n",
      "4\n",
      "y_hat---> [1.89974348, 3.79948696, 5.69923044, 7.59897392]\n",
      "e---> [0.10025652000000007, 0.20051304000000014, 0.30076956, 0.4010260800000003]\n",
      "sqr_e---> [0.010051369802510415, 0.04020547921004166, 0.09046232822259359, 0.16082191684016664]\n",
      "E---> 0.07538527351882807\n",
      "w---> 1.9072820073518828\n",
      "-------------------\n",
      "E_w[E] : 1.9072820073518828\n",
      "5\n",
      "y_hat---> [1.9072820073518828, 3.8145640147037656, 5.721846022055648, 7.629128029407531]\n",
      "e---> [0.0927179926481172, 0.1854359852962344, 0.2781539779443518, 0.3708719705924688]\n",
      "sqr_e---> [0.008596626160696315, 0.03438650464278526, 0.07736963544626696, 0.13754601857114104]\n",
      "E---> 0.06447469620522239\n",
      "w---> 1.9137294769724051\n",
      "-------------------\n",
      "E_w[E] : 1.9137294769724051\n",
      "6\n",
      "y_hat---> [1.9137294769724051, 3.8274589539448103, 5.741188430917216, 7.654917907889621]\n",
      "e---> [0.08627052302759486, 0.17254104605518972, 0.25881156908278413, 0.34508209211037943]\n",
      "sqr_e---> [0.007442603143454775, 0.0297704125738191, 0.06698342829109274, 0.1190816502952764]\n",
      "E---> 0.05581952357591075\n",
      "w---> 1.9193114293299962\n",
      "-------------------\n",
      "E_w[E] : 1.9193114293299962\n",
      "7\n",
      "y_hat---> [1.9193114293299962, 3.8386228586599924, 5.757934287989989, 7.677245717319985]\n",
      "e---> [0.08068857067000379, 0.16137714134000758, 0.24206571201001115, 0.32275428268001516]\n",
      "sqr_e---> [0.006510645436768196, 0.026042581747072784, 0.05859580893091366, 0.10417032698829114]\n",
      "E---> 0.04882984077576144\n",
      "w---> 1.9241944134075724\n",
      "-------------------\n",
      "E_w[E] : 1.9241944134075724\n",
      "8\n",
      "y_hat---> [1.9241944134075724, 3.8483888268151447, 5.772583240222717, 7.696777653630289]\n",
      "e---> [0.07580558659242764, 0.15161117318485529, 0.2274167597772827, 0.30322234636971057]\n",
      "sqr_e---> [0.005746486958622046, 0.022985947834488183, 0.05171838262759831, 0.09194379133795273]\n",
      "E---> 0.04309865218966531\n",
      "w---> 1.928504278626539\n",
      "-------------------\n",
      "E_w[E] : 1.928504278626539\n",
      "9\n",
      "y_hat---> [1.928504278626539, 3.857008557253078, 5.785512835879617, 7.714017114506156]\n",
      "e---> [0.07149572137346105, 0.1429914427469221, 0.21448716412038316, 0.2859828854938442]\n",
      "sqr_e---> [0.005111638174711576, 0.020446552698846304, 0.04600474357240418, 0.08178621079538521]\n",
      "E---> 0.038337286310336824\n",
      "w---> 1.9323380072575727\n",
      "-------------------\n",
      "E_w[E] : 1.9323380072575727\n",
      "10\n",
      "y_hat---> [1.9323380072575727, 3.8646760145151453, 5.797014021772718, 7.729352029030291]\n",
      "e---> [0.06766199274242735, 0.1353239854848547, 0.20298597822728226, 0.2706479709697094]\n",
      "sqr_e---> [0.004578145261876291, 0.018312581047505164, 0.04120330735688671, 0.07325032419002066]\n",
      "E---> 0.034336089464072204\n",
      "w---> 1.93577161620398\n",
      "-------------------\n",
      "E_w[E] : 1.93577161620398\n",
      "{10.799999999999999: 1.88, 0.10800000000000021: 1.8907999999999998, 0.08943480000000026: 1.89974348, 0.07538527351882807: 1.9072820073518828, 0.06447469620522239: 1.9137294769724051, 0.05581952357591075: 1.9193114293299962, 0.04882984077576144: 1.9241944134075724, 0.04309865218966531: 1.928504278626539, 0.038337286310336824: 1.9323380072575727, 0.034336089464072204: 1.93577161620398}\n",
      "\n",
      "min error---> 0.034336089464072204\n",
      "opt weight----> 1.93577161620398\n"
     ]
    }
   ],
   "source": [
    "import math\n",
    "x = [1,2,3,4]\n",
    "y = [2,4,6,8]\n",
    "n = len(x)\n",
    "w = 0.8\n",
    "b = 0\n",
    "alpha = 0.1\n",
    "iterations = 10\n",
    "\n",
    "def hyp(x, w, b):\n",
    "    y_hat=[]\n",
    "    for xi in x:\n",
    "        y_hat.append((w*xi) + b)\n",
    "    return y_hat\n",
    "\n",
    "def cost(y, y_hat):\n",
    "    e = [(y[i] - y_hat[i]) for i in range(n)]; print('e--->', e)\n",
    "    sq_error = [ (i**2) for i in e]; print('sqr_e--->', sq_error)\n",
    "    E = sum(sq_error)/n\n",
    "    return E\n",
    "\n",
    "def gd(w, E):\n",
    "    w = w - (-(E*alpha))    \n",
    "    return w\n",
    "\n",
    "def regression(x, y, w, b):\n",
    "    E_w={}\n",
    "\n",
    "    for i in range(iterations):\n",
    "        print(i+1)    \n",
    "        y_hat = hyp(x, w, b); print('y_hat--->', y_hat)\n",
    "        E = cost(y, y_hat); print ('E--->', E)\n",
    "        w = gd(w, E); print ('w--->', w)\n",
    "        E_w[E]=w\n",
    "        print(\"-------------------\");print(f\"E_w[E] : {E_w[E]}\")\n",
    "\n",
    "    print(E_w)\n",
    "    print(\"\")\n",
    "    print(\"min error--->\", min(E_w))\n",
    "    print(\"opt weight---->\", E_w[min(E_w)])\n",
    "\n",
    "regression(x, y, w, b)"
   ]
  },
  {
   "cell_type": "code",
   "execution_count": 36,
   "metadata": {},
   "outputs": [
    {
     "name": "stdout",
     "output_type": "stream",
     "text": [
      " 27           0 BUILD_MAP                0\n",
      "              2 STORE_FAST               4 (E_w)\n",
      "\n",
      " 29           4 SETUP_LOOP             124 (to 130)\n",
      "              6 LOAD_GLOBAL              0 (range)\n",
      "              8 LOAD_GLOBAL              1 (iterations)\n",
      "             10 CALL_FUNCTION            1\n",
      "             12 GET_ITER\n",
      "        >>   14 FOR_ITER               112 (to 128)\n",
      "             16 STORE_FAST               5 (i)\n",
      "\n",
      " 30          18 LOAD_GLOBAL              2 (print)\n",
      "             20 LOAD_FAST                5 (i)\n",
      "             22 LOAD_CONST               1 (1)\n",
      "             24 BINARY_ADD\n",
      "             26 CALL_FUNCTION            1\n",
      "             28 POP_TOP\n",
      "\n",
      " 31          30 LOAD_GLOBAL              3 (hyp)\n",
      "             32 LOAD_FAST                0 (x)\n",
      "             34 LOAD_FAST                2 (w)\n",
      "             36 LOAD_FAST                3 (b)\n",
      "             38 CALL_FUNCTION            3\n",
      "             40 STORE_FAST               6 (y_hat)\n",
      "             42 LOAD_GLOBAL              2 (print)\n",
      "             44 LOAD_CONST               2 ('y_hat--->')\n",
      "             46 LOAD_FAST                6 (y_hat)\n",
      "             48 CALL_FUNCTION            2\n",
      "             50 POP_TOP\n",
      "\n",
      " 32          52 LOAD_GLOBAL              4 (cost)\n",
      "             54 LOAD_FAST                1 (y)\n",
      "             56 LOAD_FAST                6 (y_hat)\n",
      "             58 CALL_FUNCTION            2\n",
      "             60 STORE_FAST               7 (E)\n",
      "             62 LOAD_GLOBAL              2 (print)\n",
      "             64 LOAD_CONST               3 ('E--->')\n",
      "             66 LOAD_FAST                7 (E)\n",
      "             68 CALL_FUNCTION            2\n",
      "             70 POP_TOP\n",
      "\n",
      " 33          72 LOAD_GLOBAL              5 (gd)\n",
      "             74 LOAD_FAST                2 (w)\n",
      "             76 LOAD_FAST                7 (E)\n",
      "             78 CALL_FUNCTION            2\n",
      "             80 STORE_FAST               2 (w)\n",
      "             82 LOAD_GLOBAL              2 (print)\n",
      "             84 LOAD_CONST               4 ('w--->')\n",
      "             86 LOAD_FAST                2 (w)\n",
      "             88 CALL_FUNCTION            2\n",
      "             90 POP_TOP\n",
      "\n",
      " 34          92 LOAD_FAST                2 (w)\n",
      "             94 LOAD_FAST                4 (E_w)\n",
      "             96 LOAD_FAST                7 (E)\n",
      "             98 STORE_SUBSCR\n",
      "\n",
      " 35         100 LOAD_GLOBAL              2 (print)\n",
      "            102 LOAD_CONST               5 ('-------------------')\n",
      "            104 CALL_FUNCTION            1\n",
      "            106 POP_TOP\n",
      "            108 LOAD_GLOBAL              2 (print)\n",
      "            110 LOAD_CONST               6 ('E_w[E] : ')\n",
      "            112 LOAD_FAST                4 (E_w)\n",
      "            114 LOAD_FAST                7 (E)\n",
      "            116 BINARY_SUBSCR\n",
      "            118 FORMAT_VALUE             0\n",
      "            120 BUILD_STRING             2\n",
      "            122 CALL_FUNCTION            1\n",
      "            124 POP_TOP\n",
      "            126 JUMP_ABSOLUTE           14\n",
      "        >>  128 POP_BLOCK\n",
      "\n",
      " 37     >>  130 LOAD_GLOBAL              2 (print)\n",
      "            132 LOAD_FAST                4 (E_w)\n",
      "            134 CALL_FUNCTION            1\n",
      "            136 POP_TOP\n",
      "\n",
      " 38         138 LOAD_GLOBAL              2 (print)\n",
      "            140 LOAD_CONST               7 ('')\n",
      "            142 CALL_FUNCTION            1\n",
      "            144 POP_TOP\n",
      "\n",
      " 39         146 LOAD_GLOBAL              2 (print)\n",
      "            148 LOAD_CONST               8 ('min error--->')\n",
      "            150 LOAD_GLOBAL              6 (min)\n",
      "            152 LOAD_FAST                4 (E_w)\n",
      "            154 CALL_FUNCTION            1\n",
      "            156 CALL_FUNCTION            2\n",
      "            158 POP_TOP\n",
      "\n",
      " 40         160 LOAD_GLOBAL              2 (print)\n",
      "            162 LOAD_CONST               9 ('opt weight---->')\n",
      "            164 LOAD_FAST                4 (E_w)\n",
      "            166 LOAD_GLOBAL              6 (min)\n",
      "            168 LOAD_FAST                4 (E_w)\n",
      "            170 CALL_FUNCTION            1\n",
      "            172 BINARY_SUBSCR\n",
      "            174 CALL_FUNCTION            2\n",
      "            176 POP_TOP\n",
      "            178 LOAD_CONST               0 (None)\n",
      "            180 RETURN_VALUE\n"
     ]
    }
   ],
   "source": [
    "dis.dis(regression)"
   ]
  },
  {
   "cell_type": "code",
   "execution_count": null,
   "metadata": {},
   "outputs": [],
   "source": []
  }
 ],
 "metadata": {
  "kernelspec": {
   "display_name": "Python 3",
   "language": "python",
   "name": "python3"
  },
  "language_info": {
   "codemirror_mode": {
    "name": "ipython",
    "version": 3
   },
   "file_extension": ".py",
   "mimetype": "text/x-python",
   "name": "python",
   "nbconvert_exporter": "python",
   "pygments_lexer": "ipython3",
   "version": "3.6.5"
  }
 },
 "nbformat": 4,
 "nbformat_minor": 2
}
